README.md
setup.py
pias/__init__.py
pias/agglomeration_model.py
pias/edge_feature_cache.py
pias/edge_labels.py
pias/edges.py
pias/random_forest.py
pias/server.py
pias/solver_server.py
pias/version_info.py
pias/workflow.py
pias.egg-info/PKG-INFO
pias.egg-info/SOURCES.txt
pias.egg-info/dependency_links.txt
pias.egg-info/entry_points.txt
pias.egg-info/requires.txt
pias.egg-info/top_level.txt
pias/ext/__init__.py
pias/threading/__init__.py
pias/threading/atomic_integer.py
pias/threading/countdown_latch.py
pias/zmq_util/__init__.py
pias/zmq_util/util.py