Metadata-Version: 2.1
Name: pias
Version: 0.1.0.dev0
Summary: Interactive agglomeration scheme for paintera
Home-page: https://github.com/saalfeldlab/pias
Author: Philipp Hanslovsky
Author-email: hanslovskyp@janelia.hhmi.org
License: Public domain
Platform: UNKNOWN
Requires-Python: >=3.6
